media/logo.png
static/index.html
static/style.css
tok2me/__init__.py
tok2me/__main__.py
tok2me/__version__.py
tok2me/cli.py
tok2me/codeblock.py
tok2me/commands.py
tok2me/config.py
tok2me/constants.py
tok2me/dirs.py
tok2me/eval/__init__.py
tok2me/eval/__main__.py
tok2me/eval/agents.py
tok2me/eval/execenv.py
tok2me/eval/filestore.py
tok2me/eval/main.py
tok2me/eval/run.py
tok2me/eval/suites/__init__.py
tok2me/eval/suites/basic.py
tok2me/eval/suites/browser.py
tok2me/eval/suites/init_projects.py
tok2me/eval/types.py
tok2me/init.py
tok2me/llm.py
tok2me/llm_anthropic.py
tok2me/llm_openai.py
tok2me/llm_openai_models.py
tok2me/logmanager.py
tok2me/message.py
tok2me/models.py
tok2me/prompts.py
tok2me/py.typed
tok2me/reduce.py
tok2me/server/__init__.py
tok2me/server/__main__.py
tok2me/server/api.py
tok2me/server/cli.py
tok2me/tabcomplete.py
tok2me/tools/__init__.py
tok2me/tools/_browser_playwright.py
tok2me/tools/base.py
tok2me/tools/browser.py
tok2me/tools/chats.py
tok2me/tools/gh.py
tok2me/tools/patch.py
tok2me/tools/python.py
tok2me/tools/read.py
tok2me/tools/save.py
tok2me/tools/screenshot.py
tok2me/tools/shell.py
tok2me/tools/subagent.py
tok2me/tools/tmux.py
tok2me/tools/vision.py
tok2me/tools/youtube.py
tok2me/useredit.py
tok2me/util.py
tok2me_python-0.1.0.dist-info/LICENSE
tok2me_python-0.1.0.dist-info/METADATA
tok2me_python-0.1.0.dist-info/WHEEL
tok2me_python-0.1.0.dist-info/entry_points.txt
tok2me_python-0.1.0.dist-info/RECORD
