Metadata-Version: 2.1
Name: tok2me-python
Version: 0.1.0
Summary: A fancy CLI of Tok2Me.
License: APACHE 2.0
Author: jerry zhang
Author-email: jerry.zhang.bill@gmail.com
Requires-Python: >=3.10,<4.0
Classifier: License :: Other/Proprietary License
Classifier: Programming Language :: Python :: 3
Classifier: Programming Language :: Python :: 3.10
Classifier: Programming Language :: Python :: 3.11
Classifier: Programming Language :: Python :: 3.12
Provides-Extra: all
Provides-Extra: browser
Provides-Extra: datascience
Provides-Extra: server
Requires-Dist: anthropic (>=0.34.0,<0.35.0)
Requires-Dist: bashlex (>=0.18,<0.19)
Requires-Dist: click (>=8.0,<9.0)
Requires-Dist: flask (>=3.0,<4.0) ; extra == "server" or extra == "all"
Requires-Dist: ipython (>=8.17.2,<9.0.0)
Requires-Dist: lxml
Requires-Dist: matplotlib ; extra == "datascience" or extra == "all"
Requires-Dist: multiprocessing-logging (>=0.3.4,<0.4.0)
Requires-Dist: numpy ; extra == "datascience" or extra == "all"
Requires-Dist: openai (>=1.0,<2.0)
Requires-Dist: pandas ; extra == "datascience" or extra == "all"
Requires-Dist: pick (>=2.2.0,<3.0.0)
Requires-Dist: pillow ; extra == "datascience" or extra == "all"
Requires-Dist: platformdirs (>=4.3,<5.0)
Requires-Dist: playwright (==1.47.*) ; extra == "browser" or extra == "all"
Requires-Dist: python-dotenv (>=1.0.0,<2.0.0)
Requires-Dist: rich (>=13.5.2,<14.0.0)
Requires-Dist: tabulate
Requires-Dist: tiktoken (>=0.7,<0.8)
Requires-Dist: tomlkit
Requires-Dist: typing-extensions
Requires-Dist: youtube_transcript_api (>=0.6.1,<0.7.0)
